setup.cfg
setup.py
buildSIMPLE/__init__.py
buildSIMPLE.egg-info/PKG-INFO
buildSIMPLE.egg-info/SOURCES.txt
buildSIMPLE.egg-info/dependency_links.txt
buildSIMPLE.egg-info/top_level.txt